LICENSE
MANIFEST.in
README.rst
requirements.txt
setup.cfg
setup.py
rube/__init__.py
rube.core.egg-info/PKG-INFO
rube.core.egg-info/SOURCES.txt
rube.core.egg-info/dependency_links.txt
rube.core.egg-info/namespace_packages.txt
rube.core.egg-info/not-zip-safe
rube.core.egg-info/requires.txt
rube.core.egg-info/top_level.txt
rube/core/__init__.py
rube/core/utils.py